MANIFEST.in
README.rst
requirements.txt
setup.cfg
setup.py
classin/__init__.py
classin.egg-info/PKG-INFO
classin.egg-info/SOURCES.txt
classin.egg-info/dependency_links.txt
classin.egg-info/not-zip-safe
classin.egg-info/requires.txt
classin.egg-info/top_level.txt
classin/client/__init__.py
classin/client/base.py
classin/client/api/__init__.py
classin/client/api/base.py
classin/client/api/broadcast.py
classin/client/api/classroom.py
classin/client/api/cloud.py
classin/client/api/group.py
classin/client/api/school.py
classin/client/api/user.py
classin/core/__init__.py
classin/core/exceptions.py
classin/core/utils.py